elastic_agent_setup/__init__.py
elastic_agent_setup/__main__.py
elastic_agent_setup/core.py
elastic_agent_setup/download.py
elastic_agent_setup/elastic_agent.py
elastic_agent_setup/preflight.py
elastic_agent_setup/settings.py
elastic_agent_setup/api/__init__.py
elastic_agent_setup/api/check_fleet_agents_setup.py
elastic_agent_setup/api/check_fleet_setup.py
elastic_agent_setup/api/check_service.py
elastic_agent_setup/api/create_enrollment_key.py
elastic_agent_setup/api/delete_enrollment_key.py
elastic_agent_setup/api/get_enrollment_key.py
elastic_agent_setup/api/get_enrollment_keys.py
elastic_agent_setup/api/get_fleet_agent_policy_id.py
elastic_agent_setup/api/setup_fleet.py
elastic_agent_setup/api/setup_fleet_agents.py
elastic_agent_setup/data/logging.yml
elastic_agent_setup/platform/__init__.py
elastic_agent_setup/platform/linux.py
elastic_agent_setup/platform/macos.py
elastic_agent_setup/platform/platform.py
elastic_agent_setup/platform/windows.py
elastic_agent_setup/utils/__init__.py
elastic_agent_setup/utils/exceptions.py
elastic_agent_setup/utils/logger.py
elastic_agent_setup/utils/version.py
elastic_agent_setup-0.0.11.dist-info/LICENSE.md
elastic_agent_setup-0.0.11.dist-info/METADATA
elastic_agent_setup-0.0.11.dist-info/WHEEL
elastic_agent_setup-0.0.11.dist-info/entry_points.txt
elastic_agent_setup-0.0.11.dist-info/top_level.txt
elastic_agent_setup-0.0.11.dist-info/RECORD
