Metadata-Version: 2.1
Name: elastic-agent-setup
Version: 0.0.11
Summary: A Python package used to install and enroll the Elastic Agent on multiple operating systems. Created using carcass
Home-page: https://github.com/MSAdministrator/elastic-agent-setup
Author: MSAdministrator
Author-email: rickardja@live.com
License: MIT
Keywords: carcass
Platform: UNKNOWN
Requires-Python: >=3.6, <4
Requires-Dist: pyyaml (==5.4.1)
Requires-Dist: fire (==0.3.1)
Requires-Dist: requests (==2.25.1)
